statbotics/__init__.py
statbotics/constants.py
statbotics/main.py
statbotics/validate.py
statbotics-2.0.3.dist-info/METADATA
statbotics-2.0.3.dist-info/WHEEL
statbotics-2.0.3.dist-info/RECORD
