Metadata-Version: 2.1
Name: statbotics
Version: 2.0.3
Summary: Modernizing FRC Data Analytics
Home-page: https://statbotics.io
License: MIT
Keywords: FIRST,robotics,data,analysis,ranking
Author: Abhijit Gupta
Author-email: avgupta456@gmail.com
Requires-Python: >=3.8,<4.0
Classifier: License :: OSI Approved :: MIT License
Classifier: Programming Language :: Python :: 3
Classifier: Programming Language :: Python :: 3.8
Classifier: Programming Language :: Python :: 3.9
Classifier: Programming Language :: Python :: 3.10
Classifier: Programming Language :: Python :: 3.11
Requires-Dist: cachecontrol (>=0.12.11,<0.13.0)
Requires-Dist: requests (>=2.28.2,<3.0.0)
Project-URL: Repository, https://github.com/avgupta456/statbotics
